{"cameraMode":{"drawMode":0,"name":"Shaded","section":"Shading Mode"},"sceneLighting":false,"audioPlay":false,"sceneViewState":{"m_AlwaysRefresh":false,"showFog":true,"showSkybox":false,"showFlares":true,"showImageEffects":true,"showParticleSystems":true,"showVisualEffectGraphs":true,"m_FxEnabled":true},"in2DMode":false,"pivot":{"x":23.335729598999025,"y":15.953431129455567,"z":-24.189407348632814},"rotation":{"x":0.23898935317993165,"y":-0.5218329429626465,"z":0.15515393018722535,"w":0.8042212724685669},"size":2.102294921875,"orthographic":false}